{
  "drinks": [
    {
      "idDrink": "11007",
      "strDrink": "Margarita",
      "strCategory": "Ordinary Drink",
      "strIBA": "Contemporary Classics"
    },
    {
      "idDrink": "11118",
      "strDrink": "Blue Margarita",
      "strCategory": "Ordinary Drink",
      "strIBA": null
    },
    {
      "idDrink": "16158",
      "strDrink": "Whitecap Margarita",
      "strCategory": "Other/Unknown",
      "strIBA": null
    },
    {
      "idDrink": "12322",
      "strDrink": "Strawberry Margarita",
      "strCategory": "Ordinary Drink",
      "strIBA": null
    }
  ]
}
